ngcpp/__init__.py
ngcpp/cli/cluster_info.py
ngcpp/cli/conf/__init__.py
ngcpp/cli/conf/debug.yaml
ngcpp/cli/conf/hydra/default.yaml
ngcpp/cli/conf/sync.yaml
ngcpp/cli/debug.py
ngcpp/cli/init.py
ngcpp/cli/job_info.py
ngcpp/cli/resume.py
ngcpp/cli/sync.py
ngcpp/cluster.py
ngcpp/cluster.yaml
ngcpp/jobs.py
ngcpp/utils.py
ngcpp-0.2.6.dist-info/METADATA
ngcpp-0.2.6.dist-info/WHEEL
ngcpp-0.2.6.dist-info/entry_points.txt
ngcpp-0.2.6.dist-info/RECORD
