Metadata-Version: 2.1
Name: ngcpp
Version: 0.2.6
Summary: A toolkit for ngc
License: MIT
Keywords: jam,experiment,ngc
Author: Qinsheng
Author-email: qsh.zh27@gmail.com
Requires-Python: >=3.8,<3.12
Classifier: License :: OSI Approved :: MIT License
Classifier: Programming Language :: Python :: 3
Classifier: Programming Language :: Python :: 3.8
Classifier: Programming Language :: Python :: 3.9
Classifier: Programming Language :: Python :: 3.10
Classifier: Programming Language :: Python :: 3.11
Requires-Dist: hydra-core (>=1.1.0,<2.0.0)
Requires-Dist: loguru (>=0.7.0,<0.8.0)
Requires-Dist: pandas (>=1.5.3,<2.0.0)
Requires-Dist: pyfzf (>=0.2.2,<0.3.0)
Requires-Dist: requests (>=2.31.0,<3.0.0)
Requires-Dist: tqdm (>=4.65.0,<5.0.0)
Requires-Dist: typer (>=0.3.2,<0.4.0)
